LICENSE
MANIFEST.in
setup.py
cjptools/__init__.py
cjptools.egg-info/PKG-INFO
cjptools.egg-info/SOURCES.txt
cjptools.egg-info/dependency_links.txt
cjptools.egg-info/entry_points.txt
cjptools.egg-info/requires.txt
cjptools.egg-info/top_level.txt
cjptools/arxiv/__init__.py
cjptools/invoke_help/__init__.py
cjptools/lang_trans/__init__.py
cjptools/qrcode/__init__.py
cjptools/random/__init__.py
cjptools/sys/__init__.py
cjptools/time/__init__.py