Metadata-Version: 2.1
Name: cjptools
Version: 0.2.3
Summary: My Personal Toolkit
Author: Cai Jianping
Author-email: jpingcai@163.com
License: MIT Licence
Keywords: database,localServer
Platform: any
License-File: LICENSE
Requires-Dist: numpy
